<annotation><filename>509.jpg</filename><folder>users/jugil//labels/p24_femoral01</folder><source><submittedBy>julian gil</submittedBy></source><imagesize><nrows>360</nrows><ncols>279</ncols></imagesize><object><name>1</name><deleted>0</deleted><verified>0</verified><occluded>no</occluded><attributes></attributes><parts><hasparts></hasparts><ispartof></ispartof></parts><date>25-Oct-2017 01:29:39</date><id>0</id><polygon><username>anonymous</username><pt><x>3</x><y>135</y></pt><pt><x>25</x><y>133</y></pt><pt><x>41</x><y>133</y></pt><pt><x>61</x><y>133</y></pt><pt><x>85</x><y>133</y></pt><pt><x>111</x><y>133</y></pt><pt><x>132</x><y>132</y></pt><pt><x>142</x><y>132</y></pt><pt><x>138</x><y>150</y></pt><pt><x>122</x><y>178</y></pt><pt><x>90</x><y>207</y></pt><pt><x>67</x><y>212</y></pt><pt><x>43</x><y>212</y></pt><pt><x>23</x><y>191</y></pt><pt><x>19</x><y>177</y></pt><pt><x>14</x><y>157</y></pt><pt><x>6</x><y>147</y></pt></polygon></object></annotation>